PartSeg_stardist/__init__.py
PartSeg_stardist/stardist_plugin.py
PartSeg_stardist/version.py
PartSeg_stardist-0.1.0.dist-info/METADATA
PartSeg_stardist-0.1.0.dist-info/WHEEL
PartSeg_stardist-0.1.0.dist-info/entry_points.txt
PartSeg_stardist-0.1.0.dist-info/top_level.txt
PartSeg_stardist-0.1.0.dist-info/RECORD
