Metadata-Version: 2.1
Name: PartSeg-stardist
Version: 0.1.0
Summary: PartSeg plugin to use stardist,
Home-page: https://4dnucleome.cent.uw.edu.pl/PartSeg/
Author: Grzegorz Bokota
Author-email: g.bokota@cent.uw.edu.pl
License: BSD-3-Clause
Project-URL: Source Code, https://github.com/4DNucleome/PartSeg_cellpose
Keywords: bioimaging,stardist
Platform: Linux
Platform: Windows
Platform: MacOs
Classifier: Development Status :: 3 - Alpha
Classifier: License :: OSI Approved :: BSD License
Classifier: Operating System :: OS Independent
Classifier: Programming Language :: Python :: 3
Classifier: Programming Language :: Python :: 3 :: Only
Classifier: Programming Language :: Python :: 3.6
Classifier: Programming Language :: Python :: 3.7
Classifier: Programming Language :: Python :: 3.8
Classifier: Programming Language :: Python :: Implementation :: CPython
Classifier: Topic :: Scientific/Engineering :: Bio-Informatics
Requires-Python: >=3.6
Requires-Dist: PartSeg (>=0.11.0b1)
Requires-Dist: stardist
Requires-Dist: tensorflow (<2)
